{
  "kind": "singleType",
  "collectionName": "applications",
  "info": {
    "singularName": "application",
    "pluralName": "applications",
    "displayName": "Application",
    "description": ""
  },
  "options": {
    "draftAndPublish": true
  },
  "pluginOptions": {
    "i18n": {
      "localized": true
    }
  },
  "attributes": {
    "header": {
      "type": "component",
      "repeatable": false,
      "component": "global.header",
      "pluginOptions": {
        "i18n": {
          "localized": true
        }
      }
    },
    "subTitle": {
      "type": "string",
      "pluginOptions": {
        "i18n": {
          "localized": true
        }
      }
    },
    "title": {
      "type": "string",
      "pluginOptions": {
        "i18n": {
          "localized": true
        }
      }
    },
    "description": {
      "type": "text",
      "pluginOptions": {
        "i18n": {
          "localized": true
        }
      }
    },
    "applications": {
      "displayName": "applicaitons",
      "type": "component",
      "repeatable": true,
      "component": "applications.applicaitons",
      "pluginOptions": {
        "i18n": {
          "localized": true
        }
      }
    }
  }
}
